apca/__init__.py
apca/models.py
augmented_pca-0.3.0.dist-info/LICENSE
augmented_pca-0.3.0.dist-info/METADATA
augmented_pca-0.3.0.dist-info/WHEEL
augmented_pca-0.3.0.dist-info/top_level.txt
augmented_pca-0.3.0.dist-info/RECORD
