Metadata-Version: 2.1
Name: augmented-pca
Version: 0.3.0
Summary: Python implementations of supervised and adversarial linear factor models.
Home-page: https://github.com/wecarsoniv/augmented-pca
Author: Billy Carson
Author-email: williamcarsoniv@gmail.com
Project-URL: Issue Tracker, https://github.com/wecarsoniv/augmented-pca/issues
Keywords: augmentedpca,augmented principal component analysis,augmented pca,principal component analysis,pca,factor model,factor models,linear models,autoencoder,autoencoders,supervised autoencoder,supervised autoencoders,SAE,adversarial autoencoder,adversarial autoencoders,fair machine learning,machine learning,representation learning,dimensionality reduction
Classifier: Programming Language :: Python :: 3
Classifier: License :: OSI Approved :: MIT License
Classifier: Operating System :: OS Independent
Requires-Python: >=3.11
License-File: LICENSE
Requires-Dist: numpy
Requires-Dist: scipy
